README.txt
bootstrap.py
buildout.cfg
logo.svg
setup.cfg
setup.py
collective/__init__.py
collective.harlequin.egg-info/PKG-INFO
collective.harlequin.egg-info/SOURCES.txt
collective.harlequin.egg-info/dependency_links.txt
collective.harlequin.egg-info/entry_points.txt
collective.harlequin.egg-info/namespace_packages.txt
collective.harlequin.egg-info/not-zip-safe
collective.harlequin.egg-info/paster_plugins.txt
collective.harlequin.egg-info/requires.txt
collective.harlequin.egg-info/top_level.txt
collective/harlequin/__init__.py
collective/harlequin/configure.zcml
collective/harlequin/forms.py
collective/harlequin/interfaces.py
collective/harlequin/quickinstaller.py
collective/harlequin/rebuild_i18n.sh
collective/harlequin/storage.py
collective/harlequin/Extensions/Install.py
collective/harlequin/Extensions/__init__.py
collective/harlequin/browser/__init__.py
collective/harlequin/browser/base.pt
collective/harlequin/browser/base.py
collective/harlequin/browser/configure.zcml
collective/harlequin/example/__init__.py
collective/harlequin/example/browser.py
collective/harlequin/example/configure.zcml
collective/harlequin/example/example.pt
collective/harlequin/locales/collective.harlequin.pot
collective/harlequin/locales/en/LC_MESSAGES/collective.harlequin.po
collective/harlequin/locales/fr/LC_MESSAGES/collective.harlequin.po
collective/harlequin/profiles/default/metadata.xml
collective/harlequin/profiles/default/propertiestool.xml
collective/harlequin/tests/__init__.py
collective/harlequin/tests/base.py
collective/harlequin/tests/test_browser.py
collective/harlequin/tests/test_doctest.py
collective/harlequin/tests/test_example.py
collective/harlequin/tests/test_storage.py
collective/harlequin/tests/utils.py
docs/HISTORY.txt
docs/INSTALL.txt
docs/LICENSE.GPL
docs/LICENSE.txt