Metadata-Version: 1.0
Name: collective.harlequin
Version: 1.0b4
Summary: System based on annotation to make a configurable browser view by Makina Corpus.
Home-page: http://svn.plone.org/svn/collective/collective.harlequin
Author: JeanMichel FRANCOIS aka toutpt
Author-email: jeanmichel.francois@makina-corpus.com
License: GPL
Keywords: zope plone
Platform: UNKNOWN
Classifier: Framework :: Plone
Classifier: Programming Language :: Python
